Metadata-Version: 1.2
Name: mw4
Version: 0.106
Summary: tooling for a 10micron mount
Home-page: https://github.com/mworion/MountWizzard4
Author: mw
Author-email: michael@wuertenberger.org
License: APL 2.0
Platform: UNKNOWN
Requires-Python: >=3.7.2
